{
	"$schema": "http://schema.management.azure.com/schemas/2015-01-01/deploymentTemplate.json#",
	"contentVersion": "1.0.0.0",
	"parameters": {
		"factoryName": {
			"type": "string",
			"metadata": "Data Factory name",
			"defaultValue": "devopsuacDF"
		}
	},
	"variables": {
		"factoryId": "[concat('Microsoft.DataFactory/factories/', parameters('factoryName'))]"
	},
	"resources": [
		{
			"name": "[concat(parameters('factoryName'), '/DevopsUacPipeline')]",
			"type": "Microsoft.DataFactory/factories/pipelines",
			"apiVersion": "2018-06-01",
			"properties": {
				"activities": [
					{
						"name": "DevopsUacCopyData",
						"type": "Copy",
						"dependsOn": [],
						"policy": {
							"timeout": "7.00:00:00",
							"retry": 0,
							"retryIntervalInSeconds": 30,
							"secureOutput": false,
							"secureInput": false
						},
						"userProperties": [],
						"typeProperties": {
							"source": {
								"type": "RestSource",
								"httpRequestTimeout": "00:01:40",
								"requestInterval": "00.00:00:00.010",
								"requestMethod": "GET",
								"additionalHeaders": {
									"Content-Type": "application/json"
								}
							},
							"sink": {
								"type": "JsonSink",
								"storeSettings": {
									"type": "AzureBlobStorageWriteSettings"
								},
								"formatSettings": {
									"type": "JsonWriteSettings",
									"quoteAllText": true
								}
							},
							"enableStaging": false
						},
						"inputs": [
							{
								"referenceName": "UacRestResource2",
								"type": "DatasetReference"
							}
						],
						"outputs": [
							{
								"referenceName": "StbTestUacOutputJson",
								"type": "DatasetReference"
							}
						]
					}
				],
				"annotations": []
			},
			"dependsOn": [
				"[concat(variables('factoryId'), '/datasets/UacRestResource2')]",
				"[concat(variables('factoryId'), '/datasets/StbTestUacOutputJson')]"
			]
		},
		{
			"name": "[concat(parameters('factoryName'), '/StbTestUacOutputJson')]",
			"type": "Microsoft.DataFactory/factories/datasets",
			"apiVersion": "2018-06-01",
			"properties": {
				"linkedServiceName": {
					"referenceName": "UacDevopsBlobStorage",
					"type": "LinkedServiceReference"
				},
				"annotations": [],
				"type": "Json",
				"typeProperties": {
					"location": {
						"type": "AzureBlobStorageLocation",
						"container": "uacdevops"
					}
				}
			},
			"dependsOn": []
		},
		{
			"name": "[concat(parameters('factoryName'), '/UacRestResource2')]",
			"type": "Microsoft.DataFactory/factories/datasets",
			"apiVersion": "2018-06-01",
			"properties": {
				"linkedServiceName": {
					"referenceName": "UacRestService2",
					"type": "LinkedServiceReference"
				},
				"annotations": [],
				"type": "RestResource",
				"typeProperties": {
					"relativeUrl": "opswise/resources/credentials/list"
				},
				"schema": []
			},
			"dependsOn": [
				"[concat(variables('factoryId'), '/linkedServices/UacRestService2')]"
			]
		},
		{
			"name": "[concat(parameters('factoryName'), '/UacRestService2')]",
			"type": "Microsoft.DataFactory/factories/linkedServices",
			"apiVersion": "2018-06-01",
			"properties": {
				"annotations": [],
				"type": "RestService",
				"typeProperties": {
					"url": "http://10.100.10.6:8080",
					"enableServerCertificateValidation": true,
					"authenticationType": "Basic",
					"userName": "ops.admin",
					"password": {
						"type": "SecureString",
						"value": "**********"
					}
				}
			},
			"dependsOn": []
		}
	]
}